PythonZiranyuyanChuliDierBanFix1/README.md
PythonZiranyuyanChuliDierBanFix1/__init__.py
PythonZiranyuyanChuliDierBanFix1/__main__.py
PythonZiranyuyanChuliDierBanFix1/file.epub
PythonZiranyuyanChuliDierBanFix1/index.html
PythonZiranyuyanChuliDierBanFix1/css/__init__.py
PythonZiranyuyanChuliDierBanFix1/css/annotations.css
PythonZiranyuyanChuliDierBanFix1/css/main.css
PythonZiranyuyanChuliDierBanFix1/css/normalize.css
PythonZiranyuyanChuliDierBanFix1/css/popup.css
PythonZiranyuyanChuliDierBanFix1/font/__init__.py
PythonZiranyuyanChuliDierBanFix1/font/fontello.eot
PythonZiranyuyanChuliDierBanFix1/font/fontello.svg
PythonZiranyuyanChuliDierBanFix1/font/fontello.ttf
PythonZiranyuyanChuliDierBanFix1/font/fontello.woff
PythonZiranyuyanChuliDierBanFix1/img/__init__.py
PythonZiranyuyanChuliDierBanFix1/img/annotator-glyph-sprite.png
PythonZiranyuyanChuliDierBanFix1/img/annotator-icon-sprite.png
PythonZiranyuyanChuliDierBanFix1/img/apple-touch-icon.png
PythonZiranyuyanChuliDierBanFix1/img/cancelfullscreen.png
PythonZiranyuyanChuliDierBanFix1/img/close.png
PythonZiranyuyanChuliDierBanFix1/img/fullscreen.png
PythonZiranyuyanChuliDierBanFix1/img/loader.gif
PythonZiranyuyanChuliDierBanFix1/img/menu-icon.png
PythonZiranyuyanChuliDierBanFix1/img/save.png
PythonZiranyuyanChuliDierBanFix1/img/saved.png
PythonZiranyuyanChuliDierBanFix1/img/settings-s.png
PythonZiranyuyanChuliDierBanFix1/img/settings.png
PythonZiranyuyanChuliDierBanFix1/img/star.png
PythonZiranyuyanChuliDierBanFix1/js/__init__.py
PythonZiranyuyanChuliDierBanFix1/js/epub.js
PythonZiranyuyanChuliDierBanFix1/js/epub.min.js
PythonZiranyuyanChuliDierBanFix1/js/epub.min.map
PythonZiranyuyanChuliDierBanFix1/js/hooks.min.js
PythonZiranyuyanChuliDierBanFix1/js/hooks.min.map
PythonZiranyuyanChuliDierBanFix1/js/reader.js
PythonZiranyuyanChuliDierBanFix1/js/reader.js.map
PythonZiranyuyanChuliDierBanFix1/js/reader.min.js
PythonZiranyuyanChuliDierBanFix1/js/reader.min.map
PythonZiranyuyanChuliDierBanFix1/js/hooks/__init__.py
python_ziranyuyan_chuli_dier_ban_fix1-2024.3.6.0.dist-info/METADATA
python_ziranyuyan_chuli_dier_ban_fix1-2024.3.6.0.dist-info/WHEEL
python_ziranyuyan_chuli_dier_ban_fix1-2024.3.6.0.dist-info/entry_points.txt
python_ziranyuyan_chuli_dier_ban_fix1-2024.3.6.0.dist-info/top_level.txt
python_ziranyuyan_chuli_dier_ban_fix1-2024.3.6.0.dist-info/RECORD
